{
  "api": {
    "CommandEvent": {
      "__compat": {
        "mdn_url": "https://developer.mozilla.org/docs/Web/API/CommandEvent",
        "spec_url": "https://html.spec.whatwg.org/multipage/interaction.html#commandevent",
        "tags": [
          "web-features:invoker-commands"
        ],
        "support": {
          "chrome": {
            "version_added": "135"
          },
          "chrome_android": "mirror",
          "edge": "mirror",
          "firefox": {
            "version_added": "preview",
            "flags": [
              {
                "type": "preference",
                "name": "dom.element.invokers.enabled",
                "value_to_set": "true"
              }
            ]
          },
          "firefox_android": "mirror",
          "oculus": "mirror",
          "opera": "mirror",
          "opera_android": "mirror",
          "safari": {
            "version_added": "preview"
          },
          "safari_ios": {
            "version_added": false
          },
          "samsunginternet_android": "mirror",
          "webview_android": "mirror",
          "webview_ios": "mirror"
        },
        "status": {
          "experimental": false,
          "standard_track": true,
          "deprecated": false
        }
      },
      "CommandEvent": {
        "__compat": {
          "description": "`CommandEvent()` constructor",
          "mdn_url": "https://developer.mozilla.org/docs/Web/API/CommandEvent/CommandEvent",
          "tags": [
            "web-features:invoker-commands"
          ],
          "support": {
            "chrome": {
              "version_added": "135"
            },
            "chrome_android": "mirror",
            "edge": "mirror",
            "firefox": {
              "version_added": "preview",
              "flags": [
                {
                  "type": "preference",
                  "name": "dom.element.invokers.enabled",
                  "value_to_set": "true"
                }
              ]
            },
            "firefox_android": "mirror",
            "oculus": "mirror",
            "opera": "mirror",
            "opera_android": "mirror",
            "safari": {
              "version_added": "preview"
            },
            "safari_ios": {
              "version_added": false
            },
            "samsunginternet_android": "mirror",
            "webview_android": "mirror",
            "webview_ios": "mirror"
          },
          "status": {
            "experimental": false,
            "standard_track": true,
            "deprecated": false
          }
        }
      },
      "command": {
        "__compat": {
          "mdn_url": "https://developer.mozilla.org/docs/Web/API/CommandEvent/command",
          "spec_url": "https://html.spec.whatwg.org/multipage/interaction.html#dom-commandevent-command",
          "tags": [
            "web-features:invoker-commands"
          ],
          "support": {
            "chrome": {
              "version_added": "135"
            },
            "chrome_android": "mirror",
            "edge": "mirror",
            "firefox": {
              "version_added": "preview",
              "flags": [
                {
                  "type": "preference",
                  "name": "dom.element.invokers.enabled",
                  "value_to_set": "true"
                }
              ]
            },
            "firefox_android": "mirror",
            "oculus": "mirror",
            "opera": "mirror",
            "opera_android": "mirror",
            "safari": {
              "version_added": "preview"
            },
            "safari_ios": "mirror",
            "samsunginternet_android": "mirror",
            "webview_android": "mirror",
            "webview_ios": "mirror"
          },
          "status": {
            "experimental": false,
            "standard_track": true,
            "deprecated": false
          }
        }
      },
      "source": {
        "__compat": {
          "mdn_url": "https://developer.mozilla.org/docs/Web/API/CommandEvent/source",
          "spec_url": "https://html.spec.whatwg.org/multipage/interaction.html#dom-commandevent-source",
          "tags": [
            "web-features:invoker-commands"
          ],
          "support": {
            "chrome": {
              "version_added": "135"
            },
            "chrome_android": "mirror",
            "edge": "mirror",
            "firefox": {
              "version_added": "preview",
              "flags": [
                {
                  "type": "preference",
                  "name": "dom.element.invokers.enabled",
                  "value_to_set": "true"
                }
              ]
            },
            "firefox_android": "mirror",
            "oculus": "mirror",
            "opera": "mirror",
            "opera_android": "mirror",
            "safari": {
              "version_added": "preview"
            },
            "safari_ios": "mirror",
            "samsunginternet_android": "mirror",
            "webview_android": "mirror",
            "webview_ios": "mirror"
          },
          "status": {
            "experimental": false,
            "standard_track": true,
            "deprecated": false
          }
        }
      }
    }
  }
}
