{
  "api": {
    "DocumentPictureInPictureEvent": {
      "__compat": {
        "mdn_url": "https://developer.mozilla.org/docs/Web/API/DocumentPictureInPictureEvent",
        "spec_url": "https://wicg.github.io/document-picture-in-picture/#documentpictureinpictureevent",
        "tags": [
          "web-features:document-picture-in-picture"
        ],
        "support": {
          "chrome": {
            "version_added": "116"
          },
          "chrome_android": {
            "version_added": false
          },
          "edge": "mirror",
          "firefox": {
            "version_added": false
          },
          "firefox_android": "mirror",
          "oculus": "mirror",
          "opera": "mirror",
          "opera_android": "mirror",
          "safari": {
            "version_added": false
          },
          "safari_ios": "mirror",
          "samsunginternet_android": "mirror",
          "webview_android": "mirror",
          "webview_ios": "mirror"
        },
        "status": {
          "experimental": true,
          "standard_track": true,
          "deprecated": false
        }
      },
      "DocumentPictureInPictureEvent": {
        "__compat": {
          "description": "`DocumentPictureInPictureEvent()` constructor",
          "mdn_url": "https://developer.mozilla.org/docs/Web/API/DocumentPictureInPictureEvent/DocumentPictureInPictureEvent",
          "spec_url": "https://wicg.github.io/document-picture-in-picture/#dom-documentpictureinpictureevent-documentpictureinpictureevent",
          "tags": [
            "web-features:document-picture-in-picture"
          ],
          "support": {
            "chrome": {
              "version_added": "116"
            },
            "chrome_android": {
              "version_added": false
            },
            "edge": "mirror",
            "firefox": {
              "version_added": false
            },
            "firefox_android": "mirror",
            "oculus": "mirror",
            "opera": "mirror",
            "opera_android": "mirror",
            "safari": {
              "version_added": false
            },
            "safari_ios": "mirror",
            "samsunginternet_android": "mirror",
            "webview_android": "mirror",
            "webview_ios": "mirror"
          },
          "status": {
            "experimental": true,
            "standard_track": true,
            "deprecated": false
          }
        }
      },
      "window": {
        "__compat": {
          "mdn_url": "https://developer.mozilla.org/docs/Web/API/DocumentPictureInPictureEvent/window",
          "spec_url": "https://wicg.github.io/document-picture-in-picture/#dom-documentpictureinpictureevent-window",
          "tags": [
            "web-features:document-picture-in-picture"
          ],
          "support": {
            "chrome": {
              "version_added": "116"
            },
            "chrome_android": {
              "version_added": false
            },
            "edge": "mirror",
            "firefox": {
              "version_added": false
            },
            "firefox_android": "mirror",
            "oculus": "mirror",
            "opera": "mirror",
            "opera_android": "mirror",
            "safari": {
              "version_added": false
            },
            "safari_ios": "mirror",
            "samsunginternet_android": "mirror",
            "webview_android": "mirror",
            "webview_ios": "mirror"
          },
          "status": {
            "experimental": true,
            "standard_track": true,
            "deprecated": false
          }
        }
      }
    }
  }
}
