{
  "api": {
    "NavigatorManagedData": {
      "__compat": {
        "spec_url": "https://wicg.github.io/WebApiDevice/managed_config/#navigatormanageddata",
        "support": {
          "chrome": {
            "version_added": "91"
          },
          "chrome_android": "mirror",
          "edge": "mirror",
          "firefox": {
            "version_added": false
          },
          "firefox_android": "mirror",
          "oculus": "mirror",
          "opera": "mirror",
          "opera_android": "mirror",
          "safari": {
            "version_added": false
          },
          "safari_ios": "mirror",
          "samsunginternet_android": "mirror",
          "webview_android": "mirror",
          "webview_ios": "mirror"
        },
        "status": {
          "experimental": true,
          "standard_track": true,
          "deprecated": false
        }
      },
      "getManagedConfiguration": {
        "__compat": {
          "spec_url": "https://wicg.github.io/WebApiDevice/managed_config/#dom-navigatormanageddata-getmanagedconfiguration",
          "support": {
            "chrome": {
              "version_added": "91"
            },
            "chrome_android": "mirror",
            "edge": "mirror",
            "firefox": {
              "version_added": false
            },
            "firefox_android": "mirror",
            "oculus": "mirror",
            "opera": "mirror",
            "opera_android": "mirror",
            "safari": {
              "version_added": false
            },
            "safari_ios": "mirror",
            "samsunginternet_android": "mirror",
            "webview_android": "mirror",
            "webview_ios": "mirror"
          },
          "status": {
            "experimental": true,
            "standard_track": true,
            "deprecated": false
          }
        }
      },
      "managedconfigurationchange_event": {
        "__compat": {
          "description": "`managedconfigurationchange` event",
          "spec_url": "https://wicg.github.io/WebApiDevice/managed_config/#onmanagedconfigurationchange-attribute",
          "support": {
            "chrome": {
              "version_added": "91"
            },
            "chrome_android": "mirror",
            "edge": "mirror",
            "firefox": {
              "version_added": false
            },
            "firefox_android": "mirror",
            "oculus": "mirror",
            "opera": "mirror",
            "opera_android": "mirror",
            "safari": {
              "version_added": false
            },
            "safari_ios": "mirror",
            "samsunginternet_android": "mirror",
            "webview_android": "mirror",
            "webview_ios": "mirror"
          },
          "status": {
            "experimental": true,
            "standard_track": true,
            "deprecated": false
          }
        }
      }
    }
  }
}
