{
  "api": {
    "RTCRtpSendParameters": {
      "__compat": {
        "mdn_url": "https://developer.mozilla.org/docs/Web/API/RTCRtpSendParameters",
        "support": {
          "chrome": {
            "version_added": "69"
          },
          "chrome_android": {
            "version_added": "69"
          },
          "edge": {
            "version_added": "≤79"
          },
          "firefox": {
            "version_added": false,
            "notes": "Firefox expects an <code><a href='https://developer.mozilla.org/docs/Web/API/RTCRtpParameters'>RTCRtpParameters</a></code> object instead."
          },
          "firefox_android": {
            "version_added": false,
            "notes": "Firefox expects an <code><a href='https://developer.mozilla.org/docs/Web/API/RTCRtpParameters'>RTCRtpParameters</a></code> object instead."
          },
          "ie": {
            "version_added": false
          },
          "opera": {
            "version_added": null
          },
          "opera_android": {
            "version_added": null
          },
          "safari": {
            "version_added": null
          },
          "safari_ios": {
            "version_added": null
          },
          "samsunginternet_android": {
            "version_added": "10.0"
          },
          "webview_android": {
            "version_added": "69"
          }
        },
        "status": {
          "experimental": false,
          "standard_track": true,
          "deprecated": false
        }
      },
      "degradationPreference": {
        "__compat": {
          "mdn_url": "https://developer.mozilla.org/docs/Web/API/RTCRtpSendParameters/degradationPreference",
          "support": {
            "chrome": {
              "version_added": false
            },
            "chrome_android": {
              "version_added": false
            },
            "edge": {
              "version_added": false
            },
            "firefox": {
              "version_added": false
            },
            "firefox_android": {
              "version_added": false
            },
            "ie": {
              "version_added": false
            },
            "opera": {
              "version_added": null
            },
            "opera_android": {
              "version_added": null
            },
            "safari": {
              "version_added": null
            },
            "safari_ios": {
              "version_added": null
            },
            "samsunginternet_android": {
              "version_added": false
            },
            "webview_android": {
              "version_added": false
            }
          },
          "status": {
            "experimental": false,
            "standard_track": true,
            "deprecated": false
          }
        }
      },
      "encodings": {
        "__compat": {
          "mdn_url": "https://developer.mozilla.org/docs/Web/API/RTCRtpSendParameters/encodings",
          "support": {
            "chrome": {
              "version_added": "69"
            },
            "chrome_android": {
              "version_added": "69"
            },
            "edge": {
              "version_added": "≤79"
            },
            "firefox": {
              "version_added": false,
              "notes": "Firefox uses <code>RTCRtpParameters.encodings</code> instead."
            },
            "firefox_android": {
              "version_added": false,
              "notes": "Firefox uses <code>RTCRtpParameters.encodings</code> instead."
            },
            "ie": {
              "version_added": false
            },
            "opera": {
              "version_added": null
            },
            "opera_android": {
              "version_added": null
            },
            "safari": {
              "version_added": null
            },
            "safari_ios": {
              "version_added": null
            },
            "samsunginternet_android": {
              "version_added": "10.0"
            },
            "webview_android": {
              "version_added": "69"
            }
          },
          "status": {
            "experimental": false,
            "standard_track": true,
            "deprecated": false
          }
        }
      },
      "priority": {
        "__compat": {
          "mdn_url": "https://developer.mozilla.org/docs/Web/API/RTCRtpSendParameters/priority",
          "support": {
            "chrome": {
              "version_added": false
            },
            "chrome_android": {
              "version_added": false
            },
            "edge": {
              "version_added": false
            },
            "firefox": {
              "version_added": false
            },
            "firefox_android": {
              "version_added": false
            },
            "ie": {
              "version_added": false
            },
            "opera": {
              "version_added": null
            },
            "opera_android": {
              "version_added": null
            },
            "safari": {
              "version_added": null
            },
            "safari_ios": {
              "version_added": null
            },
            "samsunginternet_android": {
              "version_added": false
            },
            "webview_android": {
              "version_added": false
            }
          },
          "status": {
            "experimental": false,
            "standard_track": true,
            "deprecated": false
          }
        }
      },
      "transactionId": {
        "__compat": {
          "mdn_url": "https://developer.mozilla.org/docs/Web/API/RTCRtpSendParameters/transactionId",
          "support": {
            "chrome": {
              "version_added": "69"
            },
            "chrome_android": {
              "version_added": "69"
            },
            "edge": {
              "version_added": "≤79"
            },
            "firefox": {
              "version_added": false
            },
            "firefox_android": {
              "version_added": false
            },
            "ie": {
              "version_added": false
            },
            "opera": {
              "version_added": null
            },
            "opera_android": {
              "version_added": null
            },
            "safari": {
              "version_added": null
            },
            "safari_ios": {
              "version_added": null
            },
            "samsunginternet_android": {
              "version_added": "10.0"
            },
            "webview_android": {
              "version_added": "69"
            }
          },
          "status": {
            "experimental": false,
            "standard_track": true,
            "deprecated": false
          }
        }
      }
    }
  }
}
