{
  "api": {
    "SpeechRecognitionResultList": {
      "__compat": {
        "mdn_url": "https://developer.mozilla.org/docs/Web/API/SpeechRecognitionResultList",
        "spec_url": "https://wicg.github.io/speech-api/#speechreco-resultlist",
        "support": {
          "chrome": {
            "version_added": "33"
          },
          "chrome_android": {
            "version_added": true
          },
          "edge": {
            "version_added": "≤79"
          },
          "firefox": {
            "version_added": false
          },
          "firefox_android": {
            "version_added": false
          },
          "ie": {
            "version_added": false
          },
          "opera": {
            "version_added": false
          },
          "opera_android": {
            "version_added": false
          },
          "safari": {
            "version_added": "14.1"
          },
          "safari_ios": {
            "version_added": "14.5"
          },
          "samsunginternet_android": {
            "version_added": true
          },
          "webview_android": {
            "version_added": true
          }
        },
        "status": {
          "experimental": true,
          "standard_track": true,
          "deprecated": false
        }
      },
      "item": {
        "__compat": {
          "mdn_url": "https://developer.mozilla.org/docs/Web/API/SpeechRecognitionResultList/item",
          "spec_url": "https://wicg.github.io/speech-api/#dom-speechrecognitionresultlist-item",
          "support": {
            "chrome": {
              "version_added": "33"
            },
            "chrome_android": {
              "version_added": true
            },
            "edge": {
              "version_added": "≤79"
            },
            "firefox": {
              "version_added": false
            },
            "firefox_android": {
              "version_added": false
            },
            "ie": {
              "version_added": false
            },
            "opera": {
              "version_added": false
            },
            "opera_android": {
              "version_added": false
            },
            "safari": {
              "version_added": "14.1"
            },
            "safari_ios": {
              "version_added": "14.5"
            },
            "samsunginternet_android": {
              "version_added": true
            },
            "webview_android": {
              "version_added": true
            }
          },
          "status": {
            "experimental": true,
            "standard_track": true,
            "deprecated": false
          }
        }
      },
      "length": {
        "__compat": {
          "mdn_url": "https://developer.mozilla.org/docs/Web/API/SpeechRecognitionResultList/length",
          "spec_url": "https://wicg.github.io/speech-api/#dom-speechrecognitionresultlist-length",
          "support": {
            "chrome": {
              "version_added": "33"
            },
            "chrome_android": {
              "version_added": true
            },
            "edge": {
              "version_added": "≤79"
            },
            "firefox": {
              "version_added": false
            },
            "firefox_android": {
              "version_added": false
            },
            "ie": {
              "version_added": false
            },
            "opera": {
              "version_added": false
            },
            "opera_android": {
              "version_added": false
            },
            "safari": {
              "version_added": "14.1"
            },
            "safari_ios": {
              "version_added": "14.5"
            },
            "samsunginternet_android": {
              "version_added": true
            },
            "webview_android": {
              "version_added": true
            }
          },
          "status": {
            "experimental": true,
            "standard_track": true,
            "deprecated": false
          }
        }
      }
    }
  }
}
